{1: {"id":4,"name":"test","coordinates":{"x":5,"y":23.6},"creationDate":"08.02.2024 20:09:51","numberOfParticipants":123,"albumsCount":50,"genre":"JAZZ","studio":{"name":"qwe","address":"AAAAAAAAAAAAAAAAAAAAAAAAAAAAA"}}, 2: {"id":2,"name":"NOTATEST","coordinates":{"x":28,"y":47.2},"creationDate":"08.02.2024 20:09:41","numberOfParticipants":123,"albumsCount":50,"genre":"JAZZ","studio":{"name":"qwe","address":"AAAAAAAAAAAAAAAAAAAAAAAAAAAAAAAAAA"}}, 3: {"id":1,"name":"asd","coordinates":{"x":50,"y":33.0},"numberOfParticipants":5,"albumsCount":5,"genre":"JAZZ","studio":{"name":"ads","address":"asd"}}, 4: {"id":3,"name":"NOTEST","coordinates":{"x":28,"y":12.4},"creationDate":"08.02.2024 20:08:10","numberOfParticipants":123,"albumsCount":50,"genre":"JAZZ","studio":{"name":"qwe","address":"https..."}}}